go_libs/__init__.py
go_libs/dll_path_finder.py
go_libs/go_libs.py
go_libs/lib-im2dhist.go
go_libs/make-library
im2dhisteq/__init__.py
im2dhisteq/im2dhisteq.py
im2dhisteq-1.1.0.data/scripts/im2dhisteq
im2dhisteq-1.1.0.data/scripts/vid2dhisteq
im2dhisteq-1.1.0.dist-info/LICENSE
im2dhisteq-1.1.0.dist-info/METADATA
im2dhisteq-1.1.0.dist-info/WHEEL
im2dhisteq-1.1.0.dist-info/top_level.txt
im2dhisteq-1.1.0.dist-info/RECORD
