Metadata-Version: 2.1
Name: im2dhisteq
Version: 1.1.0
Summary: This module attempts to enhance contrast of a given image by equalizing its two dimensional histogram.
Home-page: https://github.com/Mamdasn/im2dhisteq
Author: Mamdasan Sabrian
Author-email: <reach.s.farhad@gmail.com>
Keywords: python,histogram,image-processing,contrast-enhancement,histogram-equalization,image-contrast-enhancement,imhist,2dhist,hist2d,im2dhisteq,two-dimensional-histogram
Classifier: Development Status :: 3 - Alpha
Classifier: Intended Audience :: Science/Research
Classifier: License :: OSI Approved :: GNU General Public License v3 (GPLv3)
Classifier: Programming Language :: Python :: 3.8
Classifier: Operating System :: OS Independent
License-File: LICENSE
Requires-Dist: numpy
Requires-Dist: numba
Requires-Dist: im2dhist
Requires-Dist: opencv-python
Requires-Dist: tqdm
